google_csv_helper/__init__.py
google_csv_helper/adsense_csv_helper.py
google_csv_helper/cmd.py
google_csv_helper/csv_common.py
google_csv_helper/csv_helper.py
google_csv_helper/ga3_csv_helper.py
google_csv_helper/ga4_csv_helper.py
google_csv_helper/google_common.py
google_csv_helper-1.4.0.dist-info/licenses/LICENSE
google_csv_helper-1.4.0.dist-info/METADATA
google_csv_helper-1.4.0.dist-info/WHEEL
google_csv_helper-1.4.0.dist-info/entry_points.txt
google_csv_helper-1.4.0.dist-info/top_level.txt
google_csv_helper-1.4.0.dist-info/RECORD
