Metadata-Version: 2.4
Name: google-csv-helper
Version: 1.4.0
Summary: A simple tool that takes CSV reports from Google Adsense, Google Admob, and Google Analytics and outputs them in JSON / Pandas.DataFrame format.
Home-page: https://github.com/changyy/google-csv-helper
Download-URL: https://pypi.org/project/google-csv-helper/
Author: changyy
Author-email: changyy.csie@gmail.com
Keywords: python,google,csv,adsense,admob,report
Classifier: Programming Language :: Python :: 3
Classifier: Operating System :: MacOS :: MacOS X
Requires-Python: >=3.10
License-File: LICENSE
Requires-Dist: pandas
Dynamic: author
Dynamic: author-email
Dynamic: classifier
Dynamic: description
Dynamic: description-content-type
Dynamic: download-url
Dynamic: home-page
Dynamic: keywords
Dynamic: license-file
Dynamic: requires-dist
Dynamic: requires-python
Dynamic: summary
